cv2module/__init__.py
cv2module/color_filter.py
cv2module/util_functions.py
cv2module-0.1.2.dist-info/LICENSE
cv2module-0.1.2.dist-info/METADATA
cv2module-0.1.2.dist-info/WHEEL
cv2module-0.1.2.dist-info/top_level.txt
cv2module-0.1.2.dist-info/RECORD
