Metadata-Version: 2.1
Name: cv2module
Version: 0.1.2
Summary: A package that provides various functions to assist the OpenCV workflow
Home-page: https://github.com/Dhyeythumar/cv2module
Author: Dhyey Thumar
Author-email: dhyeythumar@gmail.com
License: UNKNOWN
Keywords: cv2,color,mask
Platform: UNKNOWN
Classifier: Programming Language :: Python :: 3
Classifier: License :: OSI Approved :: MIT License
Classifier: Operating System :: OS Independent
